Metadata-Version: 2.1
Name: SampleNoteBook
Version: 1.0.0
Summary: TKinter库写的一个简易记事本,版本还未齐全，后续再更新
Home-page: UNKNOWN
Author: Eno
Author-email: 
License: UNKNOWN
Platform: UNKNOWN
